haystack_integrations/components/connectors/__init__.py
haystack_integrations/components/connectors/py.typed
haystack_integrations/components/connectors/langfuse/__init__.py
haystack_integrations/components/connectors/langfuse/langfuse_connector.py
haystack_integrations/tracing/py.typed
haystack_integrations/tracing/langfuse/__init__.py
haystack_integrations/tracing/langfuse/tracer.py
langfuse_haystack-3.2.1.dist-info/METADATA
langfuse_haystack-3.2.1.dist-info/WHEEL
langfuse_haystack-3.2.1.dist-info/licenses/LICENSE.txt
langfuse_haystack-3.2.1.dist-info/RECORD
